{
    "rootUrl": "https://www.af-drinks.com",
    "baseUrl": "https://www.af-drinks.com/en-nz/collections/full-range",
    "site_name": "af-drinks",
    "seller": "seller",
    "bannerSkip": "button.af-gate__go",
    "productsLinks": "/en-nz/products/",
    "collectionLinks": "/en-nz/collections/",
    "skipCollectionLinksInProducts": true,
    "moreConfig": true,
    "selectors": {
        "header": {
            "name": "meta[property='og:title']",
            "images": "meta[property='og:image']",
            "description": "meta[property='og:description']"
        },
        "main": {
            "country": ".reversed-link.active[aria-current=\"true\"]",
            "price": ".product__price .price__regular"
        }
    },
    "level": 0,
    "purePlayer": true
}