{
	"id": "xviB2x1NPFUlXMI",
	"json": "{\"id\":\"xviB2x1NPFUlXMI\",\"url\":\"https://thealcoholfreeco.co.uk/product/mikkeller-drinkin-in-the-sun-330ml-2/\",\"uniqueKey\":\"https://thealcoholfreeco.co.uk/product/mikkeller-drinkin-in-the-sun-330ml-2\",\"method\":\"GET\",\"noRetry\":false,\"retryCount\":0,\"errorMessages\":[],\"headers\":{},\"userData\":{\"product\":{\"id\":1450,\"name\":\"MIKKELLER – DRINKIN IN THE SUN 330ML\",\"abv\":null,\"producer\":null,\"product_category\":\"Beer\",\"energy\":null,\"sugar\":null,\"price\":null,\"currency\":null,\"country\":null,\"url\":\"https://thealcoholfreeco.co.uk/product/mikkeller-drinkin-in-the-sun-330ml-2/\",\"images\":\"https://thealcoholfreeco.co.uk/wp-content/uploads/2021/09/Untitled-design-80.png\",\"description\":\"This beer is so fresh and tasty, we recommend you take it for a DRIVE! A bunch of friends, nice music, a box full of this beer, good weather and a long road. What else do you need? Besides the usual ingredients, we added real sunshine. Cheers!\",\"gluten_free\":null,\"vegan\":null,\"duplicated_with\":null,\"probability\":null,\"site_name\":\"thealcoholfreeco\",\"site_url\":\"https://thealcoholfreeco.co.uk\",\"seller_or_not_seller\":\"seller\",\"classified\":2,\"reason\":\"ABV is unclear\",\"reviewed\":0,\"subcategory\":null,\"cleaned\":0}}}",
	"method": "GET",
	"orderNo": 1748995312998,
	"retryCount": 0,
	"uniqueKey": "https://thealcoholfreeco.co.uk/product/mikkeller-drinkin-in-the-sun-330ml-2",
	"url": "https://thealcoholfreeco.co.uk/product/mikkeller-drinkin-in-the-sun-330ml-2/"
}